[{"Current horizontal": null, "Current vertical": null, "Action": 1, "Reward": 10, "Next horizontal": 822, "Next vertical": -32, "Score": 0}, {"Current horizontal": 818, "Current vertical": -33, "Action": 0, "Reward": 10, "Next horizontal": 814, "Next vertical": -34, "Score": 0}, {"Current horizontal": 814, "Current vertical": -34, "Action": 0, "Reward": 10, "Next horizontal": 810, "Next vertical": -36, "Score": 0}, {"Current horizontal": 810, "Current vertical": -36, "Action": 0, "Reward": 10, "Next horizontal": 806, "Next vertical": -38, "Score": 0}, {"Current horizontal": 806, "Current vertical": -38, "Action": 0, "Reward": 10, "Next horizontal": 802, "Next vertical": -41, "Score": 0}, {"Current horizontal": 802, "Current vertical": -41, "Action": 0, "Reward": 10, "Next horizontal": 798, "Next vertical": -44, "Score": 0}, {"Current horizontal": 798, "Current vertical": -44, "Action": 0, "Reward": 10, "Next horizontal": 794, "Next vertical": -48, "Score": 0}, {"Current horizontal": 794, "Current vertical": -48, "Action": 0, "Reward": 10, "Next horizontal": 790, "Next vertical": -52, "Score": 0}, {"Current horizontal": 790, "Current vertical": -52, "Action": 0, "Reward": 10, "Next horizontal": 786, "Next vertical": -57, "Score": 0}, {"Current horizontal": 786, "Current vertical": -57, "Action": 0, "Reward": 10, "Next horizontal": 782, "Next vertical": -62, "Score": 0}, {"Current horizontal": 782, "Current vertical": -62, "Action": 0, "Reward": 10, "Next horizontal": 778, "Next vertical": -68, "Score": 0}, {"Current horizontal": 778, "Current vertical": -68, "Action": 0, "Reward": 10, "Next horizontal": 774, "Next vertical": -74, "Score": 0}, {"Current horizontal": 774, "Current vertical": -74, "Action": 0, "Reward": 10, "Next horizontal": 770, "Next vertical": -81, "Score": 0}, {"Current horizontal": 770, "Current vertical": -81, "Action": 0, "Reward": 10, "Next horizontal": 766, "Next vertical": -88, "Score": 0}, {"Current horizontal": 766, "Current vertical": -88, "Action": 0, "Reward": 10, "Next horizontal": 762, "Next vertical": -96, "Score": 0}, {"Current horizontal": 762, "Current vertical": -96, "Action": 0, "Reward": 10, "Next horizontal": 758, "Next vertical": -104, "Score": 0}, {"Current horizontal": 758, "Current vertical": -104, "Action": 0, "Reward": 10, "Next horizontal": 754, "Next vertical": -112, "Score": 0}, {"Current horizontal": 754, "Current vertical": -112, "Action": 0, "Reward": 10, "Next horizontal": 750, "Next vertical": -120, "Score": 0}, {"Current horizontal": 750, "Current vertical": -120, "Action": 0, "Reward": 10, "Next horizontal": 746, "Next vertical": -128, "Score": 0}, {"Current horizontal": 746, "Current vertical": -128, "Action": 0, "Reward": 10, "Next horizontal": 742, "Next vertical": -136, "Score": 0}, {"Current horizontal": 742, "Current vertical": -136, "Action": 0, "Reward": 10, "Next horizontal": 738, "Next vertical": -144, "Score": 0}, {"Current horizontal": 738, "Current vertical": -144, "Action": 0, "Reward": 10, "Next horizontal": 734, "Next vertical": -152, "Score": 0}, {"Current horizontal": 734, "Current vertical": -152, "Action": 0, "Reward": 10, "Next horizontal": 730, "Next vertical": -160, "Score": 0}, {"Current horizontal": 730, "Current vertical": -160, "Action": 0, "Reward": 10, "Next horizontal": 726, "Next vertical": -168, "Score": 0}, {"Current horizontal": 726, "Current vertical": -168, "Action": 0, "Reward": 10, "Next horizontal": 722, "Next vertical": -176, "Score": 0}, {"Current horizontal": 722, "Current vertical": -176, "Action": 0, "Reward": 10, "Next horizontal": 718, "Next vertical": -184, "Score": 0}, {"Current horizontal": 718, "Current vertical": -184, "Action": 0, "Reward": 10, "Next horizontal": 714, "Next vertical": -192, "Score": 0}, {"Current horizontal": 714, "Current vertical": -192, "Action": 0, "Reward": 10, "Next horizontal": 710, "Next vertical": -200, "Score": 0}, {"Current horizontal": 710, "Current vertical": -200, "Action": 0, "Reward": 10, "Next horizontal": 706, "Next vertical": -208, "Score": 0}, {"Current horizontal": 706, "Current vertical": -208, "Action": 0, "Reward": 10, "Next horizontal": 702, "Next vertical": -216, "Score": 0}, {"Current horizontal": 702, "Current vertical": -216, "Action": 0, "Reward": 10, "Next horizontal": 698, "Next vertical": -224, "Score": 0}, {"Current horizontal": 698, "Current vertical": -224, "Action": 0, "Reward": 10, "Next horizontal": 694, "Next vertical": -232, "Score": 0}, {"Current horizontal": 694, "Current vertical": -232, "Action": 0, "Reward": 10, "Next horizontal": 690, "Next vertical": -240, "Score": 0}, {"Current horizontal": 690, "Current vertical": -240, "Action": 0, "Reward": 10, "Next horizontal": 686, "Next vertical": -248, "Score": 0}, {"Current horizontal": 686, "Current vertical": -248, "Action": 0, "Reward": 10, "Next horizontal": 682, "Next vertical": -256, "Score": 0}, {"Current horizontal": 682, "Current vertical": -256, "Action": 0, "Reward": 10, "Next horizontal": 678, "Next vertical": -264, "Score": 0}, {"Current horizontal": 678, "Current vertical": -264, "Action": 0, "Reward": 10, "Next horizontal": 674, "Next vertical": -272, "Score": 0}, {"Current horizontal": 674, "Current vertical": -272, "Action": 0, "Reward": 10, "Next horizontal": 670, "Next vertical": -280, "Score": 0}, {"Current horizontal": 670, "Current vertical": -280, "Action": 0, "Reward": 10, "Next horizontal": 666, "Next vertical": -288, "Score": 0}, {"Current horizontal": 666, "Current vertical": -288, "Action": 0, "Reward": 10, "Next horizontal": 662, "Next vertical": -296, "Score": 0}, {"Current horizontal": 666, "Current vertical": -288, "Action": 0, "Reward": -1000, "Next horizontal": null, "Next vertical": null, "Score": 0}]